disnake_components/__init__.py
disnake_components/client.py
disnake_components/component.py
disnake_components/const.py
disnake_components/dpy_overrides.py
disnake_components/http.py
disnake_components/interaction.py
disnake_components/utils.py
disnake_components/ext/filters.py
disnake_components-1.0.2.dist-info/LICENSE
disnake_components-1.0.2.dist-info/METADATA
disnake_components-1.0.2.dist-info/WHEEL
disnake_components-1.0.2.dist-info/top_level.txt
disnake_components-1.0.2.dist-info/RECORD
