Metadata-Version: 2.1
Name: disnake-components
Version: 1.0.2
Summary: An unofficial library for disnake components.
Home-page: https://github.com/LOCUS-TEAM/disnake-components
Author: Team Locus
Author-email: me@sskate.me
License: MIT License
Platform: UNKNOWN
Classifier: Intended Audience :: Developers
Classifier: License :: OSI Approved :: MIT License
Classifier: Natural Language :: English
Classifier: Operating System :: OS Independent
Classifier: Programming Language :: Python :: 3
Classifier: Programming Language :: Python :: 3.6
Classifier: Programming Language :: Python :: 3.7
Classifier: Programming Language :: Python :: 3.8
Classifier: Programming Language :: Python :: 3.9
Classifier: Topic :: Internet
Classifier: Topic :: Software Development :: Libraries :: Python Modules
Classifier: Topic :: Software Development :: Libraries
Classifier: Topic :: Utilities
Requires-Python: >=3.6
Provides-Extra: lint
Provides-Extra: readthedocs
Provides-Extra: dev
License-File: LICENSE
